setup.py
rst2hatena/__init__.py
rst2hatena/hatena_nodes.py
rst2hatena/rst2hatena.py
rst2hatena.egg-info/PKG-INFO
rst2hatena.egg-info/SOURCES.txt
rst2hatena.egg-info/dependency_links.txt
rst2hatena.egg-info/entry_points.txt
rst2hatena.egg-info/not-zip-safe
rst2hatena.egg-info/requires.txt
rst2hatena.egg-info/top_level.txt
rst2hatena/directives/__init__.py
rst2hatena/directives/autolink.py
rst2hatena/hatena_writer/__init__.py
rst2hatena/hatena_writer/base_translator.py
rst2hatena/roles/__init__.py
rst2hatena/tests/__init__.py
rst2hatena/tests/test_writer.py