Metadata-Version: 1.0
Name: rst2hatena
Version: 0.2.1
Summary: Convert reStructuredText to Hatena Diary syntax
Home-page: http://bitbucket.org/ae35/rst2hatena
Author: Yosuke Ikeda
Author-email: alpha.echo.35@gmail.com
License: BSD
Keywords: hatena restructuredtext
Platform: UNKNOWN
Classifier: Development Status :: 4 - Beta
Classifier: Environment :: Console
Classifier: Operating System :: OS Independent
Classifier: License :: OSI Approved :: BSD License
Classifier: Programming Language :: Python
Classifier: Topic :: Documentation
Classifier: Topic :: Software Development :: Libraries :: Python Modules
Classifier: Topic :: Text Processing
Classifier: Topic :: Utilities
